[
  {
    "id": "minecraft-ten",
    "width": 32,
    "variants": [
      {
        "id": "minecraft-ten-v2",
        "name": "Version 2",
        "description": "Minecraft Ten Version 2 is a newer version of Minecraft Ten with some tweaks to some characters, most notably `&` and `?`.",
        "author": "Ewan Howell"
      },
      {
        "id": "minecraft-ten-cyrillic",
        "name": "Cyrillic",
        "author": "xllifi",
        "thumbnail": "абв",
        "example": [
          "пример",
          "текст😳"
        ],
        "border": 277,
        "faces": [
          [22, 62],
          [108, 148],
          [194, 205, 245, 253]
        ],
        "ends": [
          [0, 22, 62, 84],
          [86, 108, 148, 170],
          [172, 194, 253, 275]
        ]
      }
    ]
  },
  {
    "id": "minecraft-five-bold",
    "author": "Ewan Howell",
    "width": 36,
    "height": 36,
    "border": 212,
    "faces": [
      [16, 48],
      [82, 114],
      [148, 154, 186, 194]
    ],
    "ends": [
      [0, 16, 48, 64],
      [66, 82, 114, 130],
      [132, 148, 186, 194]
    ],
    "terminatorSpace": true,
    "variants": [
      {
        "id": "minecraft-five-bold-cyrillic",
        "name": "Cyrillic",
        "author": "xllifi",
        "thumbnail": "абв",
        "example": [
          "пример",
          "текст😳"
        ],
        "border": 220,
        "faces": [
          [16, 48],
          [82, 114],
          [148, 162, 194, 202]
        ],
        "ends": [
          [0, 16, 48, 64],
          [66, 82, 114, 130],
          [132, 148, 202, 218]
        ]
      }
    ]
  },
  {
    "id": "minecraft-five-bold-block",
    "author": "Ewan Howell",
    "width": 40,
    "height": 52,
    "border": 246,
    "faces": [
      [16, 64],
      [98, 146],
      [180, 228]
    ],
    "ends": [
      [0, 16, 64, 80], 
      [82, 98, 146, 162],
      [164, 180, 228, 244]
    ],
    "autoBorder": true,
    "forcedTerminators": [310, 180, 318, 180, 6, 48],
    "overlay": true
  },
  {
    "id": "minecraft-ten-outline",
    "author": "Ewan Howell",
    "width": 32,
    "height": 60,
    "border": 186,
    "faces": [
      [0, 60],
      [62, 122],
      [124, 184]
    ],
    "ends": [
      [0, 0, 60, 60],
      [62, 62, 122, 122],
      [124, 124, 184, 184]
    ],
    "borderless": true,
    "forcedTerminators": [254, 124, 264, 124, 8, 60],
    "flat": true
  },
  {
    "id": "minecraft-dungeons",
    "author": "ShrimpSnail & Ewan Howell",
    "width": 32,
    "height": 44,
    "border": 266,
    "faces": [
      [22, 62],
      [108, 148],
      [194, 194, 234, 242]
    ],
    "ends": [
      [0, 22, 62, 84],
      [86, 108, 148, 170],
      [172, 194, 242, 264]
    ]
  },
  {
    "id": "minecraft-gui",
    "author": "Ewan Howell",
    "width": 40,
    "height": 44,
    "border": 126,
    "faces": [
      [0, 40],
      [42, 82],
      [84, 124 ]
    ],
    "ends": [
      [0, 0, 40, 40],
      [42, 42, 82, 82],
      [84, 84, 124, 124]
    ],
    "autoBorder": true,
    "forcedTerminators": [684, 84, 688, 84, 2, 40],
    "overlay": true,
    "flat": true
  },
  {
    "id": "minecraft-seven",
    "author": "Ewan Howell",
    "width": 34,
    "height": 46,
    "border": 234,
    "faces": [
      [16, 58],
      [92, 134],
      [168, 168, 210, 216]
    ],
    "ends": [
      [0, 16, 58, 74],
      [76, 92, 134, 150],
      [152, 168, 216, 232]
    ],
    "terminatorSpace": true
  }
]