{
	"credit": "By Ewan Howell",
	"texture_size": [1000, 320],
	"textures": {
		"1": "minecraft-ten-cyrillic:flat",
		"particle": "minecraft-ten-cyrillic:flat"
	},
	"elements": [
		{
			"from": [-16, 2, -3],
			"to": [32, 42, 19],
			"faces": {
				"north": {"uv": [4.96, 10.25, 5.728, 12.25], "texture": "#1"},
				"south": {"uv": [5.728, 10.25, 4.96, 12.25], "texture": "#1"},
				"up": {"uv": [5.728, 9.7, 4.96, 8.6], "texture": "#1"},
				"down": {"uv": [5.728, 13.75, 4.96, 12.65], "texture": "#1"}
			}
		},
		{
			"from": [-14, 44, -5],
			"to": [34, 0, 21],
			"faces": {
				"north": {"uv": [0, 13.85, 0.016, 13.9], "texture": "#1"},
				"east": {"uv": [0, 13.85, 0.016, 13.9], "texture": "#1"},
				"south": {"uv": [0, 13.85, 0.016, 13.9], "texture": "#1"},
				"west": {"uv": [0.16, 14.1, 0.176, 14.65], "texture": "#1"},
				"up": {"uv": [0.176, 14, 0.272, 14.05], "texture": "#1"},
				"down": {"uv": [0, 13.85, 0.016, 13.9], "texture": "#1"}
			}
		},
		{
			"from": [-18, 12, -5],
			"to": [-6, -8, 21],
			"faces": {
				"north": {"uv": [0, 13.85, 0.016, 13.9], "texture": "#1"},
				"east": {"uv": [0.144, 14.35, 0.16, 14.1], "texture": "#1"},
				"south": {"uv": [0, 13.85, 0.016, 13.9], "texture": "#1"},
				"west": {"uv": [0, 13.85, 0.016, 13.9], "texture": "#1"},
				"up": {"uv": [0, 13.85, 0.016, 13.9], "texture": "#1"},
				"down": {"uv": [0.208, 14.1, 0.16, 14.15], "texture": "#1"}
			}
		},
		{
			"from": [-16, -6, -3],
			"to": [-8, 2, 19],
			"faces": {
				"north": {"uv": [5.6, 12.25, 5.728, 12.65], "texture": "#1"},
				"south": {"uv": [5.6, 12.25, 5.728, 12.65], "texture": "#1"},
				"west": {"uv": [0, 13.85, 0.016, 13.9], "texture": "#1"},
				"down": {"uv": [5.888, 13.75, 5.76, 12.65], "texture": "#1"}
			}
		}
	]
}