{
	"credit": "By Ewan Howell",
	"texture_size": [1000, 320],
	"textures": {
		"0": "minecraft-five-bold:flat"
	},
	"elements": [
		{
			"from": [2, 14, 0],
			"to": [14, 22, 16],
			"faces": {
				"north": {"uv": [10.176, 4.7, 10.368, 5.1], "texture": "#0"},
				"south": {"uv": [10.368, 4.7, 10.176, 5.1], "texture": "#0"},
				"up": {"uv": [10.368, 4.1, 10.176, 3.3], "texture": "#0"},
				"down": {"uv": [10.368, 6.5, 10.176, 5.7], "texture": "#0"}
			}
		},
		{
			"from": [16, 24, 18],
			"to": [0, 12, -2],
			"faces": {
				"north": {"uv": [0, 10.6, 0.016, 10.65], "texture": "#0"},
				"east": {"uv": [0, 10.6, 0.016, 10.65], "texture": "#0"},
				"south": {"uv": [0, 10.6, 0.016, 10.65], "texture": "#0"},
				"west": {"uv": [0, 10.6, 0.016, 10.65], "texture": "#0"},
				"up": {"uv": [0, 10.6, 0.016, 10.65], "texture": "#0"},
				"down": {"uv": [0, 10.6, 0.016, 10.65], "texture": "#0"}
			}
		}
	]
}