{
	"credit": "By Ewan Howell",
	"texture_size": [1000, 320],
	"textures": {
		"0": "minecraft-five-bold-cyrillic:flat"
	},
	"elements": [
		{
			"from": [-8, 2, 0],
			"to": [24, 34, 16],
			"faces": {
				"north": {"uv": [5.824, 8.1, 6.336, 9.7], "texture": "#0"},
				"south": {"uv": [6.336, 8.1, 5.824, 9.7], "texture": "#0"},
				"up": {"uv": [6.336, 7.4, 5.824, 6.6], "texture": "#0"},
				"down": {"uv": [6.336, 10.1, 5.824, 10.9], "texture": "#0"}
			}
		},
		{
			"from": [-8, -6, 0],
			"to": [0, 2, 16],
			"faces": {
				"north": {"uv": [6.208, 9.7, 6.336, 10.1], "texture": "#0"},
				"south": {"uv": [6.336, 9.7, 6.208, 10.1], "texture": "#0"},
				"down": {"uv": [6.496, 10.1, 6.368, 10.9], "texture": "#0"}
			}
		},
		{
			"from": [26, 36, 18],
			"to": [-10, -8, -2],
			"faces": {
				"north": {"uv": [1.52, 11.85, 1.424, 11.3], "texture": "#0"},
				"east": {"uv": [1.504, 11.85, 1.52, 11.3], "texture": "#0"},
				"south": {"uv": [1.424, 11.85, 1.52, 11.3], "texture": "#0"},
				"west": {"uv": [1.424, 11.85, 1.44, 11.3], "texture": "#0"},
				"up": {"uv": [1.424, 11.85, 1.52, 11.8], "texture": "#0"},
				"down": {"uv": [1.424, 11.35, 1.52, 11.3], "texture": "#0"}
			}
		},
		{
			"from": [8, 12, -2],
			"to": [14, 36, 18],
			"faces": {
				"east": {"uv": [0, 11, 0.016, 11.05], "texture": "#0"},
				"west": {"uv": [0, 11, 0.016, 11.05], "texture": "#0"},
				"down": {"uv": [0, 11, 0.016, 11.05], "texture": "#0"}
			}
		},
		{
			"from": [-10, 12, -2],
			"to": [-4, 36, 18],
			"faces": {
				"east": {"uv": [0, 11, 0.016, 11.05], "texture": "#0"},
				"down": {"uv": [0, 11, 0.016, 11.05], "texture": "#0"}
			}
		},
		{
			"from": [2, -8, -2],
			"to": [26, 0, 18],
			"faces": {
				"west": {"uv": [0, 11, 0.016, 11.05], "texture": "#0"},
				"up": {"uv": [0, 11, 0.016, 11.05], "texture": "#0"}
			}
		}
	]
}