{
	"credit": "Made with Blockbench",
	"texture_size": [1000, 320],
	"textures": {
		"0": "mcfont-serif-template",
		"particle": "mcfont-serif-template"
	},
	"elements": [
		{
			"name": "main",
			"from": [-12, 2, -2],
			"to": [28, 42, 20],
			"faces": {
				"north": {"uv": [6.368, 1.1, 7.008, 3.1], "texture": "#0"},
				"east": {"uv": [1.936, 9, 2.288, 11], "texture": "#0"},
				"south": {"uv": [7.008, 1.1, 6.368, 3.1], "texture": "#0"},
				"west": {"uv": [1.936, 9, 2.288, 11], "texture": "#0"},
				"up": {"uv": [7.008, 0, 6.368, 1.1], "texture": "#0"},
				"down": {"uv": [7.008, 3.1, 6.368, 4.2], "texture": "#0"}
			}
		},
		{
			"name": "border",
			"from": [30, 44, 22],
			"to": [-14, 0, -4],
			"faces": {
				"north": {"uv": [3.904, 14.5, 3.552, 13.4], "texture": "#0"},
				"east": {"uv": [3.904, 14.5, 3.936, 13.4], "texture": "#0"},
				"south": {"uv": [3.552, 14.5, 3.904, 13.4], "texture": "#0"},
				"west": {"uv": [3.52, 14.5, 3.552, 13.4], "texture": "#0"},
				"up": {"uv": [3.552, 14.5, 3.904, 14.6], "texture": "#0"},
				"down": {"uv": [3.552, 13.3, 3.904, 13.4], "texture": "#0"}
			}
		},
		{
			"from": [26, 12, -4],
			"to": [30, 32, 22],
			"faces": {
				"north": {"uv": [2.08, 8.7, 2.144, 9.7], "texture": "#0"},
				"east": {"uv": [1.904, 8.6, 2.32, 9.6], "texture": "#0"},
				"south": {"uv": [2.016, 8.7, 2.08, 9.7], "texture": "#0"},
				"west": {"uv": [0.032, 14.5, 0.064, 14.6], "texture": "#0"},
				"up": {"uv": [0.032, 14.5, 0.064, 14.6], "texture": "#0"},
				"down": {"uv": [0.032, 14.5, 0.064, 14.6], "texture": "#0"}
			}
		},
		{
			"from": [-6, 16, -4],
			"to": [-2, 24, 22],
			"faces": {
				"north": {"uv": [2.08, 8.7, 2.144, 9.7], "texture": "#0"},
				"east": {"uv": [0.032, 14.5, 0.064, 14.6], "texture": "#0"},
				"south": {"uv": [2.016, 8.7, 2.08, 9.7], "texture": "#0"},
				"west": {"uv": [2.224, 8.95, 2.256, 9.05], "texture": "#0"},
				"up": {"uv": [0.032, 14.5, 0.064, 14.6], "texture": "#0"},
				"down": {"uv": [0.032, 14.5, 0.064, 14.6], "texture": "#0"}
			}
		},
		{
			"from": [-10, 12, -4],
			"to": [-6, 16, 22],
			"faces": {
				"north": {"uv": [2.08, 8.7, 2.144, 9.7], "texture": "#0"},
				"east": {"uv": [0.032, 14.5, 0.064, 14.6], "texture": "#0"},
				"south": {"uv": [2.016, 8.7, 2.08, 9.7], "texture": "#0"},
				"west": {"uv": [2.224, 8.95, 2.256, 9.05], "texture": "#0"},
				"up": {"uv": [2.208, 9.3, 2.24, 9.4], "texture": "#0"},
				"down": {"uv": [0.032, 14.5, 0.064, 14.6], "texture": "#0"}
			}
		},
		{
			"from": [-14, 8, -4],
			"to": [-10, 12, 22],
			"faces": {
				"north": {"uv": [2.08, 8.7, 2.144, 9.7], "texture": "#0"},
				"east": {"uv": [0.032, 14.5, 0.064, 14.6], "texture": "#0"},
				"south": {"uv": [2.016, 8.7, 2.08, 9.7], "texture": "#0"},
				"west": {"uv": [2.224, 8.95, 2.256, 9.05], "texture": "#0"},
				"up": {"uv": [2.24, 9.3, 2.272, 9.4], "texture": "#0"},
				"down": {"uv": [0.032, 14.5, 0.064, 14.6], "texture": "#0"}
			}
		},
		{
			"from": [-10, 24, -4],
			"to": [-6, 32, 22],
			"faces": {
				"north": {"uv": [2.08, 8.7, 2.144, 9.7], "texture": "#0"},
				"east": {"uv": [0.032, 14.5, 0.064, 14.6], "texture": "#0"},
				"south": {"uv": [2.016, 8.7, 2.08, 9.7], "texture": "#0"},
				"west": {"uv": [2.224, 8.95, 2.256, 9.05], "texture": "#0"},
				"up": {"uv": [0.032, 14.5, 0.064, 14.6], "texture": "#0"},
				"down": {"uv": [2.224, 9.1, 2.256, 9.2], "texture": "#0"}
			}
		},
		{
			"from": [-14, 32, -4],
			"to": [-10, 36, 22],
			"faces": {
				"north": {"uv": [2.08, 8.7, 2.144, 9.7], "texture": "#0"},
				"east": {"uv": [0.032, 14.5, 0.064, 14.6], "texture": "#0"},
				"south": {"uv": [2.016, 8.7, 2.08, 9.7], "texture": "#0"},
				"west": {"uv": [2.224, 8.95, 2.256, 9.05], "texture": "#0"},
				"up": {"uv": [0.032, 14.5, 0.064, 14.6], "texture": "#0"},
				"down": {"uv": [2.224, 9.1, 2.256, 9.2], "texture": "#0"}
			}
		}
	]
}